yehua/__init__.py
yehua/__main__.py
yehua/_version.py
yehua/cookiecutter.py
yehua/cookiecutter_to_yehua.py
yehua/main.py
yehua/project.py
yehua/theme.py
yehua/utils.py
yehua/thirdparty/__init__.py
yehua/thirdparty/cutie.py
yehua-0.1.4.dist-info/LICENSE
yehua-0.1.4.dist-info/METADATA
yehua-0.1.4.dist-info/WHEEL
yehua-0.1.4.dist-info/entry_points.txt
yehua-0.1.4.dist-info/top_level.txt
yehua-0.1.4.dist-info/RECORD
