Metadata-Version: 2.1
Name: yehua
Version: 0.1.4
Summary: Yet another a project template tool for an organisation.
Home-page: https://github.com/moremoban/yehua
Author: chfw
Author-email: wangc_2011@hotmail.com
License: New BSD
Download-URL: https://github.com/moremoban/yehua/archive/0.1.4.tar.gz
Keywords: python
Platform: UNKNOWN
Classifier: Topic :: Software Development :: Libraries
Classifier: Programming Language :: Python
Classifier: Intended Audience :: Developers
Classifier: Programming Language :: Python :: 3 :: Only
Classifier: Programming Language :: Python :: 3.6
Classifier: Programming Language :: Python :: 3.7
Classifier: Programming Language :: Python :: 3.8
Classifier: Topic :: Utilities
Requires-Python: >=3.6
Requires-Dist: Jinja2
Requires-Dist: moban (>=0.6.0)
Requires-Dist: colorful
Requires-Dist: rich
Requires-Dist: readchar
Requires-Dist: colorama
Requires-Dist: moban-jinja2-github (>=0.0.2)
Requires-Dist: moban-ansible
Requires-Dist: ruamel.yaml (>=0.15.5) ; python_version != '3.4' and python_version < '3.7'
Requires-Dist: ruamel.yaml (>=0.15.42) ; python_version == '3.7'
Requires-Dist: ruamel.yaml (>=0.15.98) ; python_version == '3.8'
Provides-Extra: cookiecutter
Requires-Dist: cookiecutter (==1.7.0) ; extra == 'cookiecutter'
Provides-Extra: pypi-mobans
Requires-Dist: pypi-mobans-pkg (>=0.1.4) ; extra == 'pypi-mobans'
